<?xml version="1.0" encoding="UTF-8"?>

<ConformanceContext xmlns:xsi="http://www.w3.org/2001/XMLSchema-instance" UUID="5be0dca884aeb311e25203b8" xsi:noNamespaceSchemaLocation="https://raw.githubusercontent.com/Jungyubw/NIST_healthcare_hl7_v2_profile_schema/master/Schema/NIST%20Validation%20Schema/ConformanceContext.xsd">
  <MetaData Date="Mon Nov 05 19:13:28 EST 2018" Name="Contextbased Constrations" OrgName="NIST" Status="Draft" Version="No Version Info"/>
  <Constraints>
    <Message>
      <ByID ID="5a81af6984ae50488e8800a2">
        <Constraint ID="Content" Target="1[1].15[1]">
          <Reference GeneratedBy="Test Case Authoring &amp; Management Tool(TCAMT)" ReferencePath="MSH[1].15[1]" Source="testcase" TestDataCategorization="Value-Test Case Fixed"/>
          <Description>Invalid content (based on test case fixed data). The value at MSH-15 (Accept Acknowledgment Type) does not match the expected value: 'NE'.</Description>
          <Assertion>
            <PlainText IgnoreCase="true" Path="1[1].15[1]" Text="NE"/>
          </Assertion>
        </Constraint>
        <Constraint ID="Content" Target="1[1].16[1]">
          <Reference GeneratedBy="Test Case Authoring &amp; Management Tool(TCAMT)" ReferencePath="MSH[1].16[1]" Source="testcase" TestDataCategorization="Value-Test Case Fixed"/>
          <Description>Invalid content (based on test case fixed data). The value at MSH-16 (Application Acknowledgment Type) does not match the expected value: 'NE'.</Description>
          <Assertion>
            <PlainText IgnoreCase="true" Path="1[1].16[1]" Text="NE"/>
          </Assertion>
        </Constraint>
        <Constraint ID="Content" Target="4[1].1[1]">
          <Reference GeneratedBy="Test Case Authoring &amp; Management Tool(TCAMT)" ReferencePath="MSA[1].1[1]" Source="testcase" TestDataCategorization="Value-Test Case Fixed"/>
          <Description>Invalid content (based on test case fixed data). The value at MSA-1 (Acknowledgment Code) does not match the expected value: 'CA'.</Description>
          <Assertion>
            <PlainText IgnoreCase="true" Path="4[1].1[1]" Text="CA"/>
          </Assertion>
        </Constraint>
      </ByID>
    </Message>
  </Constraints>
</ConformanceContext>
